colcon_lcov_result/__init__.py
colcon_lcov_result/task/__init__.py
colcon_lcov_result/task/lcov.py
colcon_lcov_result/verb/__init__.py
colcon_lcov_result/verb/lcov_result.py
colcon_lcov_result/verb/configuration/__init__.py
colcon_lcov_result/verb/configuration/lcovrc
colcon_lcov_result-0.5.3.dist-info/LICENSE
colcon_lcov_result-0.5.3.dist-info/METADATA
colcon_lcov_result-0.5.3.dist-info/WHEEL
colcon_lcov_result-0.5.3.dist-info/entry_points.txt
colcon_lcov_result-0.5.3.dist-info/top_level.txt
colcon_lcov_result-0.5.3.dist-info/zip-safe
colcon_lcov_result-0.5.3.dist-info/RECORD
