Metadata-Version: 2.1
Name: colcon-lcov-result
Version: 0.5.3
Summary: Extension for colcon to gather test results.
Home-page: https://colcon.readthedocs.io
Author: Juan Pablo Samper
Author-email: jp.samper@apex.ai
Maintainer: Christophe Bedard
Maintainer-email: bedard.christophe@gmail.com
License: Apache License, Version 2.0
Project-URL: Changelog, https://github.com/colcon/colcon-lcov-result/milestones?state=closed
Project-URL: GitHub, https://github.com/colcon/colcon-lcov-result/
Keywords: colcon
Classifier: Development Status :: 3 - Alpha
Classifier: Environment :: Plugins
Classifier: Intended Audience :: Developers
Classifier: License :: OSI Approved :: Apache Software License
Classifier: Operating System :: POSIX
Classifier: Programming Language :: Python
Classifier: Topic :: Software Development :: Build Tools
Requires-Python: >=3.6
License-File: LICENSE
Requires-Dist: colcon-core>=0.5.6
Provides-Extra: test
Requires-Dist: flake8>=3.6.0; extra == "test"
Requires-Dist: flake8-blind-except; extra == "test"
Requires-Dist: flake8-builtins; extra == "test"
Requires-Dist: flake8-class-newline; extra == "test"
Requires-Dist: flake8-comprehensions; extra == "test"
Requires-Dist: flake8-deprecated; extra == "test"
Requires-Dist: flake8-docstrings; extra == "test"
Requires-Dist: flake8-import-order; extra == "test"
Requires-Dist: flake8-quotes; extra == "test"
Requires-Dist: pep8-naming; extra == "test"
Requires-Dist: pylint; extra == "test"
Requires-Dist: pytest; extra == "test"
Requires-Dist: pytest-cov; extra == "test"
Requires-Dist: scspell3k>=2.2; extra == "test"
